tundra/__init__.py
tundra/factory.py
tundra/util.py
tundra/algorithm/__init__.py
tundra/algorithm/misc.py
tundra/algorithm/path.py
tundra/algorithm/search.py
tundra/algorithm/spanning_tree.py
tundra/algorithm/tests.py
tundra/core/__init__.py
tundra/core/digraph.py
tundra/core/graph.py
tundra-0.2.2.dist-info/DESCRIPTION.rst
tundra-0.2.2.dist-info/METADATA
tundra-0.2.2.dist-info/RECORD
tundra-0.2.2.dist-info/WHEEL
tundra-0.2.2.dist-info/metadata.json
tundra-0.2.2.dist-info/top_level.txt
