Metadata-Version: 2.0
Name: tundra
Version: 0.2.2
Summary: Pure Python Graph Algorithms module
Home-page: https://github.com/caiopo/tundra
Author: Caio Pereira Oliveira
Author-email: caiopoliveira@gmail.com
License: MIT
Platform: UNKNOWN
Classifier: Development Status :: 3 - Alpha
Classifier: Intended Audience :: Developers
Classifier: License :: OSI Approved :: MIT License
Classifier: Natural Language :: English
Classifier: Operating System :: Unix
Classifier: Programming Language :: Python :: 3.6
